bertdotcheater/__init__.py
bertdotcheater/ascii.py
bertdotcheater/cli.py
bertdotcheater/logger.py
bertdotcheater/processor.py
bt_cheater-2.1.0.dist-info/METADATA
bt_cheater-2.1.0.dist-info/WHEEL
bt_cheater-2.1.0.dist-info/entry_points.txt
bt_cheater-2.1.0.dist-info/top_level.txt
bt_cheater-2.1.0.dist-info/RECORD
