Metadata-Version: 2.1
Name: bt-cheater
Version: 2.1.0
Summary: Bert's Cheat Notes cli
Home-page: https://github.com/berttejeda/bert.cheater
Author: Engelbert Tejeda
Author-email: berttejeda@gmail.com
Keywords: md,markdown,cheatsheet,notes,snippets
Classifier: Development Status :: 3 - Alpha
Classifier: Intended Audience :: Developers
Classifier: Intended Audience :: Information Technology
Classifier: License :: OSI Approved :: MIT License
Classifier: Natural Language :: English
Classifier: Programming Language :: Python :: 2.7
Classifier: Programming Language :: Python :: 3
Classifier: Programming Language :: Python :: 3.4
Classifier: Programming Language :: Python :: 3.5
Classifier: Programming Language :: Python :: 3.6
Classifier: Programming Language :: Python :: 3.7
Requires-Python: >=3.7
Requires-Dist: click (<8.0,>=7.0)
Requires-Dist: getversion
Requires-Dist: PyYAML (<=6.0,>=5.0)
Requires-Dist: pyaml-env (<1.2,>=1.1.5)
Requires-Dist: markdown (<4.0,>=3.4.1)
Requires-Dist: setuptools (>=40.6)
Provides-Extra: tests
Requires-Dist: pytest ; extra == 'tests'
Requires-Dist: pytest-cov ; extra == 'tests'
Requires-Dist: coveralls ; extra == 'tests'
Requires-Dist: flake8 ; extra == 'tests'
Requires-Dist: mypy ; extra == 'tests'
